ascidia/__init__.py
ascidia/__main__.py
ascidia/core.py
ascidia/main.py
ascidia/patterns.py
ascidia-2.0.1.dist-info/LICENSE.txt
ascidia-2.0.1.dist-info/METADATA
ascidia-2.0.1.dist-info/WHEEL
ascidia-2.0.1.dist-info/entry_points.txt
ascidia-2.0.1.dist-info/top_level.txt
ascidia-2.0.1.dist-info/RECORD
