Metadata-Version: 2.1
Name: ascidia
Version: 2.0.1
Summary: Technical diagrams from ASCII art, with added Markdown philosophy
Author-email: Mark Frimston <mfrimston@gmail.com>
License: MIT-License
Project-URL: Repository, https://github.com/frimkron/ascidia.git
Requires-Python: >=3.10
License-File: LICENSE.txt
Requires-Dist: pycairo ~=1.27
